deepaccess/__init__.py
deepaccess/deepaccess.py
deepaccess/ensemble_utils.py
deepaccess/interpret/ExpectedPatternEffect.py
deepaccess/interpret/__init__.py
deepaccess/interpret/importance_utils.py
deepaccess/interpret/interpret.py
deepaccess/interpret/data/HMv11_MOUSE.txt
deepaccess/interpret/data/backgrounds.fa
deepaccess/interpret/data/mm10_random_closed.10.fa
deepaccess/interpret/data/mm10_random_closed.100.fa
deepaccess/interpret/data/mm10_random_closed.25.fa
deepaccess/interpret/data/mm10_random_closed.fa
deepaccess/interpret/data/mm10_random_open.10.fa
deepaccess/interpret/data/mm10_random_open.100.fa
deepaccess/interpret/data/mm10_random_open.25.fa
deepaccess/interpret/data/mm10_random_open.fa
deepaccess/interpret/data/promoter_closed.10.fa
deepaccess/interpret/data/promoter_closed.100.fa
deepaccess/interpret/data/promoter_closed.25.fa
deepaccess/interpret/data/promoter_open.10.fa
deepaccess/interpret/data/promoter_open.100.fa
deepaccess/interpret/data/promoter_open.25.fa
deepaccess/train/CNN.py
deepaccess/train/DeepAccessModel.py
deepaccess/train/__init__.py
deepaccess/train/homer_matrix.npy
deepaccess/train/train.py
deepaccess-0.1.3.dist-info/LICENSE
deepaccess-0.1.3.dist-info/METADATA
deepaccess-0.1.3.dist-info/WHEEL
deepaccess-0.1.3.dist-info/entry_points.txt
deepaccess-0.1.3.dist-info/top_level.txt
deepaccess-0.1.3.dist-info/RECORD
