Metadata-Version: 2.1
Name: deepaccess
Version: 0.1.3
Summary: A package for training and interpreting an ensemble of neural networks for chromatin accessibility
Home-page: https://github.com/gifford-lab/deepaccess-package
Author: Jennifer Hammelman
Author-email: jhammelm@mit.edu
License: UNKNOWN
Project-URL: Bug Tracker, https://github.com/gifford-lab/deepaccess-package/issues
Platform: UNKNOWN
Classifier: Programming Language :: Python :: 3
Classifier: License :: OSI Approved :: MIT License
Classifier: Operating System :: OS Independent
Requires-Python: >=3.6
License-File: LICENSE
Requires-Dist: tensorflow (>=2.4)
Requires-Dist: keras (>=2.4.3)
Requires-Dist: scipy (>=1.6.2)
Requires-Dist: matplotlib (>=3.3.3)
Requires-Dist: numpy (>=1.19.0)
Requires-Dist: scikit-learn (>=0.24.1)
